<?xml version='1.0' encoding='utf-8'?>
<mxGraphModel grid="0">
  <root>
    <mxCell id="0" />
    <mxCell id="1" parent="0" />
    <mxCell id="node1" value="&lt;font style='font-size: 14.0px;' face='Times,serif' color='#000000'&gt;001&lt;/font&gt;" style="verticalAlign=middle;html=1;rounded=0;labelBackgroundColor=none;strokeColor=black;fillColor=white;strokeWidth=1;dashed=0;" parent="1" vertex="1">
      <mxGeometry x="449.75" y="20.029999999999973" width="43.0" height="43.0" as="geometry" />
    </mxCell>
    <mxCell id="node2" value="&lt;font style='font-size: 14.0px;' face='Times,serif' color='#000000'&gt;marr0001&lt;/font&gt;" style="rhombus;verticalAlign=middle;html=1;rounded=0;labelBackgroundColor=none;strokeColor=black;fillColor=lightgrey;strokeWidth=1;dashed=0;" parent="1" vertex="1">
      <mxGeometry x="489.0" y="115.06000000000006" width="174.5" height="50.5" as="geometry" />
    </mxCell>
    <mxCell id="node3" value="&lt;font style='font-size: 14.0px;' face='Times,serif' color='#000000'&gt;marr0002&lt;/font&gt;" style="rhombus;verticalAlign=middle;html=1;rounded=0;labelBackgroundColor=none;strokeColor=black;fillColor=lightgrey;strokeWidth=1;dashed=0;" parent="1" vertex="1">
      <mxGeometry x="223.0" y="115.06000000000006" width="174.5" height="50.5" as="geometry" />
    </mxCell>
    <mxCell id="node24" value="&lt;font style='font-size: 14.0px;' face='Times,serif' color='#000000'&gt;017&lt;/font&gt;" style="ellipse;aspect=fixed;verticalAlign=middle;html=1;rounded=0;labelBackgroundColor=none;strokeColor=black;fillColor=white;strokeWidth=1;dashed=0;" parent="1" vertex="1">
      <mxGeometry x="546.09" y="201.56000000000003" width="60.32" height="60.32" as="geometry" />
    </mxCell>
    <mxCell id="node26" value="&lt;font style='font-size: 14.0px;' face='Times,serif' color='#000000'&gt;012&lt;/font&gt;" style="ellipse;aspect=fixed;verticalAlign=middle;html=1;rounded=0;labelBackgroundColor=none;strokeColor=black;fillColor=white;strokeWidth=1;dashed=0;" parent="1" vertex="1">
      <mxGeometry x="280.09" y="201.56000000000003" width="60.32" height="60.32" as="geometry" />
    </mxCell>
    <mxCell id="node4" value="&lt;font style='font-size: 14.0px;' face='Times,serif' color='#000000'&gt;002&lt;/font&gt;" style="verticalAlign=middle;html=1;rounded=0;labelBackgroundColor=none;strokeColor=black;fillColor=white;strokeWidth=1;dashed=0;" parent="1" vertex="1">
      <mxGeometry x="892.75" y="20.029999999999973" width="43.0" height="43.0" as="geometry" />
    </mxCell>
    <mxCell id="node5" value="&lt;font style='font-size: 14.0px;' face='Times,serif' color='#000000'&gt;marr0003&lt;/font&gt;" style="rhombus;verticalAlign=middle;html=1;rounded=0;labelBackgroundColor=none;strokeColor=black;fillColor=lightgrey;strokeWidth=1;dashed=0;" parent="1" vertex="1">
      <mxGeometry x="686.0" y="115.06000000000006" width="174.5" height="50.5" as="geometry" />
    </mxCell>
    <mxCell id="node6" value="&lt;font style='font-size: 14.0px;' face='Times,serif' color='#000000'&gt;marr0004&lt;/font&gt;" style="rhombus;verticalAlign=middle;html=1;rounded=0;labelBackgroundColor=none;strokeColor=black;fillColor=lightgrey;strokeWidth=1;dashed=0;" parent="1" vertex="1">
      <mxGeometry x="776.0" y="297.89" width="174.5" height="50.5" as="geometry" />
    </mxCell>
    <mxCell id="node7" value="&lt;font style='font-size: 14.0px;' face='Times,serif' color='#000000'&gt;marr0005&lt;/font&gt;" style="rhombus;verticalAlign=middle;html=1;rounded=0;labelBackgroundColor=none;strokeColor=black;fillColor=lightgrey;strokeWidth=1;dashed=0;" parent="1" vertex="1">
      <mxGeometry x="1162.0" y="115.06000000000006" width="174.5" height="50.5" as="geometry" />
    </mxCell>
    <mxCell id="node27" value="&lt;font style='font-size: 14.0px;' face='Times,serif' color='#000000'&gt;008&lt;/font&gt;" style="verticalAlign=middle;html=1;rounded=0;labelBackgroundColor=none;strokeColor=black;fillColor=white;strokeWidth=1;dashed=0;" parent="1" vertex="1">
      <mxGeometry x="751.75" y="210.22000000000003" width="43.0" height="43.0" as="geometry" />
    </mxCell>
    <mxCell id="node28" value="&lt;font style='font-size: 14.0px;' face='Times,serif' color='#000000'&gt;011&lt;/font&gt;" style="verticalAlign=middle;html=1;rounded=0;labelBackgroundColor=none;strokeColor=black;fillColor=white;strokeWidth=1;dashed=0;" parent="1" vertex="1">
      <mxGeometry x="841.75" y="393.04999999999995" width="43.0" height="43.0" as="geometry" />
    </mxCell>
    <mxCell id="node30" value="&lt;font style='font-size: 14.0px;' face='Times,serif' color='#000000'&gt;013&lt;/font&gt;" style="verticalAlign=middle;html=1;rounded=0;labelBackgroundColor=none;strokeColor=black;fillColor=white;strokeWidth=1;dashed=0;" parent="1" vertex="1">
      <mxGeometry x="1227.75" y="210.22000000000003" width="43.0" height="43.0" as="geometry" />
    </mxCell>
    <mxCell id="node8" value="&lt;font style='font-size: 14.0px;' face='Times,serif' color='#000000'&gt;003&lt;/font&gt;" style="ellipse;aspect=fixed;verticalAlign=middle;html=1;rounded=0;labelBackgroundColor=none;strokeColor=black;fillColor=white;strokeWidth=1;dashed=0;" parent="1" vertex="1">
      <mxGeometry x="743.09" y="11.369999999999973" width="60.32" height="60.32" as="geometry" />
    </mxCell>
    <mxCell id="node9" value="&lt;font style='font-size: 14.0px;' face='Times,serif' color='#000000'&gt;004&lt;/font&gt;" style="verticalAlign=middle;html=1;rounded=0;labelBackgroundColor=none;strokeColor=black;fillColor=white;strokeWidth=1;dashed=0;" parent="1" vertex="1">
      <mxGeometry x="34.75" y="210.22000000000003" width="43.0" height="43.0" as="geometry" />
    </mxCell>
    <mxCell id="node10" value="&lt;font style='font-size: 14.0px;' face='Times,serif' color='#000000'&gt;marr0006&lt;/font&gt;" style="rhombus;verticalAlign=middle;html=1;rounded=0;labelBackgroundColor=none;strokeColor=black;fillColor=lightgrey;strokeWidth=1;dashed=0;" parent="1" vertex="1">
      <mxGeometry x="4.0" y="297.89" width="174.5" height="50.5" as="geometry" />
    </mxCell>
    <mxCell id="node31" value="&lt;font style='font-size: 14.0px;' face='Times,serif' color='#000000'&gt;010&lt;/font&gt;" style="verticalAlign=middle;html=1;rounded=0;labelBackgroundColor=none;strokeColor=black;fillColor=white;strokeWidth=1;dashed=0;" parent="1" vertex="1">
      <mxGeometry x="69.75" y="393.04999999999995" width="43.0" height="43.0" as="geometry" />
    </mxCell>
    <mxCell id="node11" value="&lt;font style='font-size: 14.0px;' face='Times,serif' color='#000000'&gt;005&lt;/font&gt;" style="verticalAlign=middle;html=1;rounded=0;labelBackgroundColor=none;strokeColor=black;fillColor=white;strokeWidth=1;dashed=0;" parent="1" vertex="1">
      <mxGeometry x="458.75" y="210.22000000000003" width="43.0" height="43.0" as="geometry" />
    </mxCell>
    <mxCell id="node12" value="&lt;font style='font-size: 14.0px;' face='Times,serif' color='#000000'&gt;marr0007&lt;/font&gt;" style="rhombus;verticalAlign=middle;html=1;rounded=0;labelBackgroundColor=none;strokeColor=black;fillColor=lightgrey;strokeWidth=1;dashed=0;" parent="1" vertex="1">
      <mxGeometry x="390.0" y="297.89" width="174.5" height="50.5" as="geometry" />
    </mxCell>
    <mxCell id="node13" value="&lt;font style='font-size: 14.0px;' face='Times,serif' color='#000000'&gt;marr0008&lt;/font&gt;" style="rhombus;verticalAlign=middle;html=1;rounded=0;labelBackgroundColor=none;strokeColor=black;fillColor=lightgrey;strokeWidth=1;dashed=0;" parent="1" vertex="1">
      <mxGeometry x="969.0" y="297.89" width="174.5" height="50.5" as="geometry" />
    </mxCell>
    <mxCell id="node14" value="&lt;font style='font-size: 14.0px;' face='Times,serif' color='#000000'&gt;marr0009&lt;/font&gt;" style="rhombus;verticalAlign=middle;html=1;rounded=0;labelBackgroundColor=none;strokeColor=black;fillColor=lightgrey;strokeWidth=1;dashed=0;" parent="1" vertex="1">
      <mxGeometry x="197.0" y="297.89" width="174.5" height="50.5" as="geometry" />
    </mxCell>
    <mxCell id="node33" value="&lt;font style='font-size: 14.0px;' face='Times,serif' color='#000000'&gt;023&lt;/font&gt;" style="ellipse;aspect=fixed;verticalAlign=middle;html=1;rounded=0;labelBackgroundColor=none;strokeColor=black;fillColor=white;strokeWidth=1;dashed=0;" parent="1" vertex="1">
      <mxGeometry x="447.09" y="384.38999999999993" width="60.32" height="60.32" as="geometry" />
    </mxCell>
    <mxCell id="node34" value="&lt;font style='font-size: 14.0px;' face='Times,serif' color='#000000'&gt;020&lt;/font&gt;" style="ellipse;aspect=fixed;verticalAlign=middle;html=1;rounded=0;labelBackgroundColor=none;strokeColor=black;fillColor=white;strokeWidth=1;dashed=0;" parent="1" vertex="1">
      <mxGeometry x="1026.09" y="384.38999999999993" width="60.32" height="60.32" as="geometry" />
    </mxCell>
    <mxCell id="node36" value="&lt;font style='font-size: 14.0px;' face='Times,serif' color='#000000'&gt;021&lt;/font&gt;" style="ellipse;aspect=fixed;verticalAlign=middle;html=1;rounded=0;labelBackgroundColor=none;strokeColor=black;fillColor=white;strokeWidth=1;dashed=0;" parent="1" vertex="1">
      <mxGeometry x="254.09" y="384.38999999999993" width="60.32" height="60.32" as="geometry" />
    </mxCell>
    <mxCell id="node15" value="&lt;font style='font-size: 14.0px;' face='Times,serif' color='#000000'&gt;006&lt;/font&gt;" style="ellipse;aspect=fixed;verticalAlign=middle;html=1;rounded=0;labelBackgroundColor=none;strokeColor=black;fillColor=white;strokeWidth=1;dashed=0;" parent="1" vertex="1">
      <mxGeometry x="826.09" y="201.56000000000003" width="60.32" height="60.32" as="geometry" />
    </mxCell>
    <mxCell id="node16" value="&lt;font style='font-size: 14.0px;' face='Times,serif' color='#000000'&gt;007&lt;/font&gt;" style="ellipse;aspect=fixed;verticalAlign=middle;html=1;rounded=0;labelBackgroundColor=none;strokeColor=black;fillColor=white;strokeWidth=1;dashed=0;" parent="1" vertex="1">
      <mxGeometry x="546.09" y="11.369999999999973" width="60.32" height="60.32" as="geometry" />
    </mxCell>
    <mxCell id="node17" value="&lt;font style='font-size: 14.0px;' face='Times,serif' color='#000000'&gt;009&lt;/font&gt;" style="ellipse;aspect=fixed;verticalAlign=middle;html=1;rounded=0;labelBackgroundColor=none;strokeColor=black;fillColor=white;strokeWidth=1;dashed=0;" parent="1" vertex="1">
      <mxGeometry x="96.09" y="201.56000000000003" width="60.32" height="60.32" as="geometry" />
    </mxCell>
    <mxCell id="node18" value="&lt;font style='font-size: 14.0px;' face='Times,serif' color='#000000'&gt;014&lt;/font&gt;" style="ellipse;aspect=fixed;verticalAlign=middle;html=1;rounded=0;labelBackgroundColor=none;strokeColor=black;fillColor=white;strokeWidth=1;dashed=0;" parent="1" vertex="1">
      <mxGeometry x="1149.09" y="201.56000000000003" width="60.32" height="60.32" as="geometry" />
    </mxCell>
    <mxCell id="node19" value="&lt;font style='font-size: 14.0px;' face='Times,serif' color='#000000'&gt;marr0012&lt;/font&gt;" style="rhombus;verticalAlign=middle;html=1;rounded=0;labelBackgroundColor=none;strokeColor=black;fillColor=lightgrey;strokeWidth=1;dashed=0;" parent="1" vertex="1">
      <mxGeometry x="1162.0" y="297.89" width="174.5" height="50.5" as="geometry" />
    </mxCell>
    <mxCell id="node41" value="&lt;font style='font-size: 14.0px;' face='Times,serif' color='#000000'&gt;019&lt;/font&gt;" style="verticalAlign=middle;html=1;rounded=0;labelBackgroundColor=none;strokeColor=black;fillColor=white;strokeWidth=1;dashed=0;" parent="1" vertex="1">
      <mxGeometry x="1227.75" y="393.04999999999995" width="43.0" height="43.0" as="geometry" />
    </mxCell>
    <mxCell id="node20" value="&lt;font style='font-size: 14.0px;' face='Times,serif' color='#000000'&gt;015&lt;/font&gt;" style="ellipse;aspect=fixed;verticalAlign=middle;html=1;rounded=0;labelBackgroundColor=none;strokeColor=black;fillColor=white;strokeWidth=1;dashed=0;" parent="1" vertex="1">
      <mxGeometry x="380.09" y="201.56000000000003" width="60.32" height="60.32" as="geometry" />
    </mxCell>
    <mxCell id="node21" value="&lt;font style='font-size: 14.0px;' face='Times,serif' color='#000000'&gt;016&lt;/font&gt;" style="ellipse;aspect=fixed;verticalAlign=middle;html=1;rounded=0;labelBackgroundColor=none;strokeColor=black;fillColor=white;strokeWidth=1;dashed=0;" parent="1" vertex="1">
      <mxGeometry x="1026.09" y="201.56000000000003" width="60.32" height="60.32" as="geometry" />
    </mxCell>
    <mxCell id="node22" value="&lt;font style='font-size: 14.0px;' face='Times,serif' color='#000000'&gt;ZZ01&lt;/font&gt;" style="ellipse;aspect=fixed;verticalAlign=middle;html=1;rounded=0;labelBackgroundColor=none;strokeColor=black;fillColor=white;strokeWidth=1;dashed=0;" parent="1" vertex="1">
      <mxGeometry x="1211.72" y="3.9999999999999716" width="75.06" height="75.06" as="geometry" />
    </mxCell>
    <mxCell id="node23" value="&lt;font style='font-size: 14.0px;' face='Times,serif' color='#000000'&gt;ZZ02&lt;/font&gt;" style="ellipse;aspect=fixed;verticalAlign=middle;html=1;rounded=0;labelBackgroundColor=none;strokeColor=black;fillColor=white;strokeWidth=1;dashed=0;" parent="1" vertex="1">
      <mxGeometry x="272.72" y="3.9999999999999716" width="75.06" height="75.06" as="geometry" />
    </mxCell>
    <mxCell id="node25" value="&lt;font style='font-size: 14.0px;' face='Times,serif' color='#000000'&gt;marr0010&lt;/font&gt;" style="rhombus;verticalAlign=middle;html=1;rounded=0;labelBackgroundColor=none;strokeColor=black;fillColor=lightgrey;strokeWidth=1;dashed=0;" parent="1" vertex="1">
      <mxGeometry x="583.0" y="297.89" width="174.5" height="50.5" as="geometry" />
    </mxCell>
    <mxCell id="node37" value="&lt;font style='font-size: 14.0px;' face='Times,serif' color='#000000'&gt;018&lt;/font&gt;" style="ellipse;aspect=fixed;verticalAlign=middle;html=1;rounded=0;labelBackgroundColor=none;strokeColor=black;fillColor=white;strokeWidth=1;dashed=0;" parent="1" vertex="1">
      <mxGeometry x="640.09" y="384.38999999999993" width="60.32" height="60.32" as="geometry" />
    </mxCell>
    <mxCell id="node29" value="&lt;font style='font-size: 14.0px;' face='Times,serif' color='#000000'&gt;marr0011&lt;/font&gt;" style="rhombus;verticalAlign=middle;html=1;rounded=0;labelBackgroundColor=none;strokeColor=black;fillColor=lightgrey;strokeWidth=1;dashed=0;" parent="1" vertex="1">
      <mxGeometry x="390.0" y="480.72" width="174.5" height="50.5" as="geometry" />
    </mxCell>
    <mxCell id="node39" value="&lt;font style='font-size: 14.0px;' face='Times,serif' color='#000000'&gt;025&lt;/font&gt;" style="ellipse;aspect=fixed;verticalAlign=middle;html=1;rounded=0;labelBackgroundColor=none;strokeColor=black;fillColor=white;strokeWidth=1;dashed=0;" parent="1" vertex="1">
      <mxGeometry x="447.09" y="567.22" width="60.32" height="60.32" as="geometry" />
    </mxCell>
    <mxCell id="node32" value="&lt;font style='font-size: 14.0px;' face='Times,serif' color='#000000'&gt;marr0013&lt;/font&gt;" style="rhombus;verticalAlign=middle;html=1;rounded=0;labelBackgroundColor=none;strokeColor=black;fillColor=lightgrey;strokeWidth=1;dashed=0;" parent="1" vertex="1">
      <mxGeometry x="197.0" y="480.72" width="174.5" height="50.5" as="geometry" />
    </mxCell>
    <mxCell id="node42" value="&lt;font style='font-size: 14.0px;' face='Times,serif' color='#000000'&gt;022&lt;/font&gt;" style="verticalAlign=middle;html=1;rounded=0;labelBackgroundColor=none;strokeColor=black;fillColor=white;strokeWidth=1;dashed=0;" parent="1" vertex="1">
      <mxGeometry x="262.75" y="575.88" width="43.0" height="43.0" as="geometry" />
    </mxCell>
    <mxCell id="node35" value="&lt;font style='font-size: 14.0px;' face='Times,serif' color='#000000'&gt;marr0014&lt;/font&gt;" style="rhombus;verticalAlign=middle;html=1;rounded=0;labelBackgroundColor=none;strokeColor=black;fillColor=lightgrey;strokeWidth=1;dashed=0;" parent="1" vertex="1">
      <mxGeometry x="969.0" y="480.72" width="174.5" height="50.5" as="geometry" />
    </mxCell>
    <mxCell id="node43" value="&lt;font style='font-size: 14.0px;' face='Times,serif' color='#000000'&gt;024&lt;/font&gt;" style="verticalAlign=middle;html=1;rounded=0;labelBackgroundColor=none;strokeColor=black;fillColor=white;strokeWidth=1;dashed=0;" parent="1" vertex="1">
      <mxGeometry x="1034.75" y="575.88" width="43.0" height="43.0" as="geometry" />
    </mxCell>
    <mxCell id="node38" value="&lt;font style='font-size: 14.0px;' face='Times,serif' color='#000000'&gt;marr0016&lt;/font&gt;" style="rhombus;verticalAlign=middle;html=1;rounded=0;labelBackgroundColor=none;strokeColor=black;fillColor=lightgrey;strokeWidth=1;dashed=0;" parent="1" vertex="1">
      <mxGeometry x="583.0" y="663.54" width="174.5" height="50.5" as="geometry" />
    </mxCell>
    <mxCell id="node46" value="&lt;font style='font-size: 14.0px;' face='Times,serif' color='#000000'&gt;026&lt;/font&gt;" style="verticalAlign=middle;html=1;rounded=0;labelBackgroundColor=none;strokeColor=black;fillColor=white;strokeWidth=1;dashed=0;" parent="1" vertex="1">
      <mxGeometry x="648.75" y="758.71" width="43.0" height="43.0" as="geometry" />
    </mxCell>
    <mxCell id="node40" value="&lt;font style='font-size: 14.0px;' face='Times,serif' color='#000000'&gt;marr0015&lt;/font&gt;" style="rhombus;verticalAlign=middle;html=1;rounded=0;labelBackgroundColor=none;strokeColor=black;fillColor=lightgrey;strokeWidth=1;dashed=0;" parent="1" vertex="1">
      <mxGeometry x="390.0" y="663.54" width="174.5" height="50.5" as="geometry" />
    </mxCell>
    <mxCell id="node44" value="&lt;font style='font-size: 14.0px;' face='Times,serif' color='#000000'&gt;027&lt;/font&gt;" style="ellipse;aspect=fixed;verticalAlign=middle;html=1;rounded=0;labelBackgroundColor=none;strokeColor=black;fillColor=white;strokeWidth=1;dashed=0;" parent="1" vertex="1">
      <mxGeometry x="447.09" y="750.0500000000001" width="60.32" height="60.32" as="geometry" />
    </mxCell>
    <mxCell id="node45" value="&lt;font style='font-size: 14.0px;' face='Times,serif' color='#000000'&gt;marr0017&lt;/font&gt;" style="rhombus;verticalAlign=middle;html=1;rounded=0;labelBackgroundColor=none;strokeColor=black;fillColor=lightgrey;strokeWidth=1;dashed=0;" parent="1" vertex="1">
      <mxGeometry x="486.0" y="846.37" width="174.5" height="50.5" as="geometry" />
    </mxCell>
    <mxCell id="node47" value="&lt;font style='font-size: 14.0px;' face='Times,serif' color='#000000'&gt;028&lt;/font&gt;" style="verticalAlign=middle;html=1;rounded=0;labelBackgroundColor=none;strokeColor=black;fillColor=grey;strokeWidth=1;dashed=0;" parent="1" vertex="1">
      <mxGeometry x="551.75" y="932.87" width="43.0" height="43.0" as="geometry" />
    </mxCell>
    <mxCell id="edge1" style="html=1;endArrow=none;dashed=0;endFill=0;startArrow=none;startFill=0;fillColor=black;strokeColor=black;strokeWidth=1;rounded=0;exitX=1.0000;exitY=0.9895;entryX=0.3837;entryY=0.0000;" parent="1" edge="1" source="node1" target="node2">
      <mxGeometry as="geometry" relative="1">
        <mxPoint x="493.01" y="62.58000000000004" as="sourcePoint" />
        <mxPoint x="555.95" y="120.60000000000002" as="targetPoint" />
      </mxGeometry>
    </mxCell>
    <mxCell id="edge2" style="html=1;endArrow=none;dashed=0;endFill=0;startArrow=none;startFill=0;fillColor=black;strokeColor=black;strokeWidth=1;rounded=0;exitX=0.0000;exitY=0.8267;entryX=0.6579;entryY=0.0000;" parent="1" edge="1" source="node1" target="node3">
      <mxGeometry as="geometry" relative="1">
        <mxPoint x="449.54" y="55.58000000000004" as="sourcePoint" />
        <mxPoint x="337.81" y="122.75" as="targetPoint" />
      </mxGeometry>
    </mxCell>
    <mxCell id="edge35" style="html=1;endArrow=none;dashed=0;endFill=0;startArrow=none;startFill=0;fillColor=black;strokeColor=black;strokeWidth=1;rounded=0;exitX=0.5000;exitY=1.0000;entryX=0.5000;entryY=0.0000;" parent="1" edge="1" source="node2" target="node24">
      <mxGeometry as="geometry" relative="1">
        <mxPoint x="576.25" y="165.74" as="sourcePoint" />
        <mxPoint x="576.25" y="201.23000000000002" as="targetPoint" />
      </mxGeometry>
    </mxCell>
    <mxCell id="edge36" style="html=1;endArrow=none;dashed=0;endFill=0;startArrow=none;startFill=0;fillColor=black;strokeColor=black;strokeWidth=1;rounded=0;exitX=0.5000;exitY=1.0000;entryX=0.5000;entryY=0.0000;" parent="1" edge="1" source="node3" target="node26">
      <mxGeometry as="geometry" relative="1">
        <mxPoint x="310.25" y="165.74" as="sourcePoint" />
        <mxPoint x="310.25" y="201.23000000000002" as="targetPoint" />
      </mxGeometry>
    </mxCell>
    <mxCell id="edge3" style="html=1;endArrow=none;dashed=0;endFill=0;startArrow=none;startFill=0;fillColor=black;strokeColor=black;strokeWidth=1;rounded=0;exitX=0.0000;exitY=0.8700;entryX=0.6451;entryY=0.0000;" parent="1" edge="1" source="node4" target="node5">
      <mxGeometry as="geometry" relative="1">
        <mxPoint x="892.53" y="57.440000000000055" as="sourcePoint" />
        <mxPoint x="798.57" y="121.92999999999995" as="targetPoint" />
      </mxGeometry>
    </mxCell>
    <mxCell id="edge4" style="html=1;endArrow=none;dashed=0;endFill=0;startArrow=none;startFill=0;fillColor=black;strokeColor=black;strokeWidth=1;curved=1;exitX=0.5214;exitY=1.0000;entryX=0.5779;entryY=0.0000;" parent="1" edge="1" source="node4" target="node6">
      <mxGeometry as="geometry" relative="1">
        <mxPoint x="915.17" y="63.299999999999955" as="sourcePoint" />
        <mxPoint x="876.84" y="301.56000000000006" as="targetPoint" />
        <Array as="points">
          <mxPoint x="918.6971452055394" y="182.52956656331355" />
          <mxPoint x="895.25" y="261.89" />
        </Array>
      </mxGeometry>
    </mxCell>
    <mxCell id="edge5" style="html=1;endArrow=none;dashed=0;endFill=0;startArrow=none;startFill=0;fillColor=black;strokeColor=black;strokeWidth=1;rounded=0;exitX=1.0000;exitY=0.6709;entryX=0.2556;entryY=0.0000;" parent="1" edge="1" source="node4" target="node7">
      <mxGeometry as="geometry" relative="1">
        <mxPoint x="936.23" y="48.879999999999995" as="sourcePoint" />
        <mxPoint x="1206.6" y="126.99000000000001" as="targetPoint" />
      </mxGeometry>
    </mxCell>
    <mxCell id="edge37" style="html=1;endArrow=none;dashed=0;endFill=0;startArrow=none;startFill=0;fillColor=black;strokeColor=black;strokeWidth=1;rounded=0;exitX=0.5000;exitY=1.0000;entryX=0.5000;entryY=0.0000;" parent="1" edge="1" source="node5" target="node27">
      <mxGeometry as="geometry" relative="1">
        <mxPoint x="773.25" y="165.74" as="sourcePoint" />
        <mxPoint x="773.25" y="209.96000000000004" as="targetPoint" />
      </mxGeometry>
    </mxCell>
    <mxCell id="edge38" style="html=1;endArrow=none;dashed=0;endFill=0;startArrow=none;startFill=0;fillColor=black;strokeColor=black;strokeWidth=1;rounded=0;exitX=0.5000;exitY=1.0000;entryX=0.5000;entryY=0.0000;" parent="1" edge="1" source="node6" target="node28">
      <mxGeometry as="geometry" relative="1">
        <mxPoint x="863.25" y="348.57000000000005" as="sourcePoint" />
        <mxPoint x="863.25" y="392.78999999999996" as="targetPoint" />
      </mxGeometry>
    </mxCell>
    <mxCell id="edge39" style="html=1;endArrow=none;dashed=0;endFill=0;startArrow=none;startFill=0;fillColor=black;strokeColor=black;strokeWidth=1;rounded=0;exitX=0.5000;exitY=1.0000;entryX=0.5000;entryY=0.0000;" parent="1" edge="1" source="node7" target="node30">
      <mxGeometry as="geometry" relative="1">
        <mxPoint x="1249.25" y="165.74" as="sourcePoint" />
        <mxPoint x="1249.25" y="209.96000000000004" as="targetPoint" />
      </mxGeometry>
    </mxCell>
    <mxCell id="edge6" style="html=1;endArrow=none;dashed=0;endFill=0;startArrow=none;startFill=0;fillColor=black;strokeColor=black;strokeWidth=1;rounded=0;exitX=0.5000;exitY=1.0000;entryX=0.5000;entryY=0.0000;" parent="1" edge="1" source="node8" target="node5">
      <mxGeometry as="geometry" relative="1">
        <mxPoint x="773.25" y="72.09000000000003" as="sourcePoint" />
        <mxPoint x="773.25" y="114.81000000000006" as="targetPoint" />
      </mxGeometry>
    </mxCell>
    <mxCell id="edge7" style="html=1;endArrow=none;dashed=0;endFill=0;startArrow=none;startFill=0;fillColor=black;strokeColor=black;strokeWidth=1;rounded=0;exitX=0.6888;exitY=1.0000;entryX=0.4502;entryY=0.0000;" parent="1" edge="1" source="node9" target="node10">
      <mxGeometry as="geometry" relative="1">
        <mxPoint x="64.37" y="253.46000000000004" as="sourcePoint" />
        <mxPoint x="82.56" y="299.95000000000005" as="targetPoint" />
      </mxGeometry>
    </mxCell>
    <mxCell id="edge40" style="html=1;endArrow=none;dashed=0;endFill=0;startArrow=none;startFill=0;fillColor=black;strokeColor=black;strokeWidth=1;rounded=0;exitX=0.5000;exitY=1.0000;entryX=0.5000;entryY=0.0000;" parent="1" edge="1" source="node10" target="node31">
      <mxGeometry as="geometry" relative="1">
        <mxPoint x="91.25" y="348.57000000000005" as="sourcePoint" />
        <mxPoint x="91.25" y="392.78999999999996" as="targetPoint" />
      </mxGeometry>
    </mxCell>
    <mxCell id="edge8" style="html=1;endArrow=none;dashed=0;endFill=0;startArrow=none;startFill=0;fillColor=black;strokeColor=black;strokeWidth=1;rounded=0;exitX=0.4837;exitY=1.0000;entryX=0.5047;entryY=0.0000;" parent="1" edge="1" source="node11" target="node12">
      <mxGeometry as="geometry" relative="1">
        <mxPoint x="479.55" y="253.46000000000004" as="sourcePoint" />
        <mxPoint x="478.07" y="297.71000000000004" as="targetPoint" />
      </mxGeometry>
    </mxCell>
    <mxCell id="edge9" style="html=1;endArrow=none;dashed=0;endFill=0;startArrow=none;startFill=0;fillColor=black;strokeColor=black;strokeWidth=1;curved=1;exitX=1.0000;exitY=0.8430;entryX=0.2555;entryY=0.0000;" parent="1" edge="1" source="node11" target="node13">
      <mxGeometry as="geometry" relative="1">
        <mxPoint x="502.16" y="246.47000000000003" as="sourcePoint" />
        <mxPoint x="1013.58" y="309.90999999999997" as="targetPoint" />
        <Array as="points">
          <mxPoint x="637.9848630049067" y="290.74773263801046" />
          <mxPoint x="876.932341748183" y="284.1777791376094" />
          <mxPoint x="959.25" y="297.89" />
        </Array>
      </mxGeometry>
    </mxCell>
    <mxCell id="edge10" style="html=1;endArrow=none;dashed=0;endFill=0;startArrow=none;startFill=0;fillColor=black;strokeColor=black;strokeWidth=1;curved=1;exitX=0.0416;exitY=1.0000;entryX=0.7637;entryY=0.0000;" parent="1" edge="1" source="node11" target="node14">
      <mxGeometry as="geometry" relative="1">
        <mxPoint x="460.54" y="253.44000000000005" as="sourcePoint" />
        <mxPoint x="330.26" y="310.76" as="targetPoint" />
        <Array as="points">
          <mxPoint x="403.74500100851304" y="289.93818192871254" />
        </Array>
      </mxGeometry>
    </mxCell>
    <mxCell id="edge41" style="html=1;endArrow=none;dashed=0;endFill=0;startArrow=none;startFill=0;fillColor=black;strokeColor=black;strokeWidth=1;rounded=0;exitX=0.5000;exitY=1.0000;entryX=0.5000;entryY=0.0000;" parent="1" edge="1" source="node12" target="node33">
      <mxGeometry as="geometry" relative="1">
        <mxPoint x="477.25" y="348.57000000000005" as="sourcePoint" />
        <mxPoint x="477.25" y="384.06000000000006" as="targetPoint" />
      </mxGeometry>
    </mxCell>
    <mxCell id="edge42" style="html=1;endArrow=none;dashed=0;endFill=0;startArrow=none;startFill=0;fillColor=black;strokeColor=black;strokeWidth=1;rounded=0;exitX=0.5000;exitY=1.0000;entryX=0.5000;entryY=0.0000;" parent="1" edge="1" source="node13" target="node34">
      <mxGeometry as="geometry" relative="1">
        <mxPoint x="1056.25" y="348.57000000000005" as="sourcePoint" />
        <mxPoint x="1056.25" y="384.06000000000006" as="targetPoint" />
      </mxGeometry>
    </mxCell>
    <mxCell id="edge43" style="html=1;endArrow=none;dashed=0;endFill=0;startArrow=none;startFill=0;fillColor=black;strokeColor=black;strokeWidth=1;rounded=0;exitX=0.5000;exitY=1.0000;entryX=0.5000;entryY=0.0000;" parent="1" edge="1" source="node14" target="node36">
      <mxGeometry as="geometry" relative="1">
        <mxPoint x="284.25" y="348.57000000000005" as="sourcePoint" />
        <mxPoint x="284.25" y="384.06000000000006" as="targetPoint" />
      </mxGeometry>
    </mxCell>
    <mxCell id="edge11" style="html=1;endArrow=none;dashed=0;endFill=0;startArrow=none;startFill=0;fillColor=black;strokeColor=black;strokeWidth=1;rounded=0;exitX=0.5380;exitY=1.0000;entryX=0.4892;entryY=0.0000;" parent="1" edge="1" source="node15" target="node6">
      <mxGeometry as="geometry" relative="1">
        <mxPoint x="858.54" y="262.0" as="sourcePoint" />
        <mxPoint x="861.37" y="298.16999999999996" as="targetPoint" />
      </mxGeometry>
    </mxCell>
    <mxCell id="edge12" style="html=1;endArrow=none;dashed=0;endFill=0;startArrow=none;startFill=0;fillColor=black;strokeColor=black;strokeWidth=1;rounded=0;exitX=0.5000;exitY=1.0000;entryX=0.5000;entryY=0.0000;" parent="1" edge="1" source="node16" target="node2">
      <mxGeometry as="geometry" relative="1">
        <mxPoint x="576.25" y="72.09000000000003" as="sourcePoint" />
        <mxPoint x="576.25" y="114.81000000000006" as="targetPoint" />
      </mxGeometry>
    </mxCell>
    <mxCell id="edge13" style="html=1;endArrow=none;dashed=0;endFill=0;startArrow=none;startFill=0;fillColor=black;strokeColor=black;strokeWidth=1;rounded=0;exitX=0.3228;exitY=1.0000;entryX=0.5495;entryY=0.0000;" parent="1" edge="1" source="node17" target="node10">
      <mxGeometry as="geometry" relative="1">
        <mxPoint x="115.56" y="260.03999999999996" as="sourcePoint" />
        <mxPoint x="99.88" y="300.08000000000004" as="targetPoint" />
      </mxGeometry>
    </mxCell>
    <mxCell id="edge14" style="html=1;endArrow=none;dashed=0;endFill=0;startArrow=none;startFill=0;fillColor=black;strokeColor=black;strokeWidth=1;rounded=0;exitX=0.8049;exitY=1.0000;entryX=0.4103;entryY=0.0000;" parent="1" edge="1" source="node18" target="node19">
      <mxGeometry as="geometry" relative="1">
        <mxPoint x="1197.64" y="256.22" as="sourcePoint" />
        <mxPoint x="1233.59" y="302.13" as="targetPoint" />
      </mxGeometry>
    </mxCell>
    <mxCell id="edge46" style="html=1;endArrow=none;dashed=0;endFill=0;startArrow=none;startFill=0;fillColor=black;strokeColor=black;strokeWidth=1;rounded=0;exitX=0.5000;exitY=1.0000;entryX=0.5000;entryY=0.0000;" parent="1" edge="1" source="node19" target="node41">
      <mxGeometry as="geometry" relative="1">
        <mxPoint x="1249.25" y="348.57000000000005" as="sourcePoint" />
        <mxPoint x="1249.25" y="392.78999999999996" as="targetPoint" />
      </mxGeometry>
    </mxCell>
    <mxCell id="edge15" style="html=1;endArrow=none;dashed=0;endFill=0;startArrow=none;startFill=0;fillColor=black;strokeColor=black;strokeWidth=1;rounded=0;exitX=0.7918;exitY=1.0000;entryX=0.4128;entryY=0.0000;" parent="1" edge="1" source="node20" target="node12">
      <mxGeometry as="geometry" relative="1">
        <mxPoint x="427.85" y="256.22" as="sourcePoint" />
        <mxPoint x="462.04" y="301.84000000000003" as="targetPoint" />
      </mxGeometry>
    </mxCell>
    <mxCell id="edge16" style="html=1;endArrow=none;dashed=0;endFill=0;startArrow=none;startFill=0;fillColor=black;strokeColor=black;strokeWidth=1;rounded=0;exitX=0.5000;exitY=1.0000;entryX=0.5000;entryY=0.0000;" parent="1" edge="1" source="node21" target="node13">
      <mxGeometry as="geometry" relative="1">
        <mxPoint x="1056.25" y="262.0" as="sourcePoint" />
        <mxPoint x="1056.25" y="297.58000000000004" as="targetPoint" />
      </mxGeometry>
    </mxCell>
    <mxCell id="edge17" style="html=1;endArrow=none;dashed=0;endFill=0;startArrow=none;startFill=0;fillColor=black;strokeColor=black;strokeWidth=1;rounded=0;exitX=0.5000;exitY=1.0000;entryX=0.5000;entryY=0.0000;" parent="1" edge="1" source="node22" target="node7">
      <mxGeometry as="geometry" relative="1">
        <mxPoint x="1249.25" y="79.39999999999998" as="sourcePoint" />
        <mxPoint x="1249.25" y="114.53999999999996" as="targetPoint" />
      </mxGeometry>
    </mxCell>
    <mxCell id="edge18" style="html=1;endArrow=none;dashed=0;endFill=0;startArrow=none;startFill=0;fillColor=black;strokeColor=black;strokeWidth=1;rounded=0;exitX=0.5000;exitY=1.0000;entryX=0.5000;entryY=0.0000;" parent="1" edge="1" source="node23" target="node3">
      <mxGeometry as="geometry" relative="1">
        <mxPoint x="310.25" y="79.39999999999998" as="sourcePoint" />
        <mxPoint x="310.25" y="114.53999999999996" as="targetPoint" />
      </mxGeometry>
    </mxCell>
    <mxCell id="edge19" style="html=1;endArrow=none;dashed=0;endFill=0;startArrow=none;startFill=0;fillColor=black;strokeColor=black;strokeWidth=1;rounded=0;exitX=1.0000;exitY=0.8530;entryX=0.3856;entryY=0.0000;" parent="1" edge="1" source="node24" target="node25">
      <mxGeometry as="geometry" relative="1">
        <mxPoint x="597.58" y="253.01" as="sourcePoint" />
        <mxPoint x="650.29" y="303.15" as="targetPoint" />
      </mxGeometry>
    </mxCell>
    <mxCell id="edge44" style="html=1;endArrow=none;dashed=0;endFill=0;startArrow=none;startFill=0;fillColor=black;strokeColor=black;strokeWidth=1;rounded=0;exitX=0.5000;exitY=1.0000;entryX=0.5000;entryY=0.0000;" parent="1" edge="1" source="node25" target="node37">
      <mxGeometry as="geometry" relative="1">
        <mxPoint x="670.25" y="348.57000000000005" as="sourcePoint" />
        <mxPoint x="670.25" y="384.06000000000006" as="targetPoint" />
      </mxGeometry>
    </mxCell>
    <mxCell id="edge20" style="html=1;endArrow=none;dashed=0;endFill=0;startArrow=none;startFill=0;fillColor=black;strokeColor=black;strokeWidth=1;rounded=0;exitX=0.3636;exitY=1.0000;entryX=0.5379;entryY=0.0000;" parent="1" edge="1" source="node26" target="node14">
      <mxGeometry as="geometry" relative="1">
        <mxPoint x="302.02" y="261.02" as="sourcePoint" />
        <mxPoint x="290.86" y="299.4" as="targetPoint" />
      </mxGeometry>
    </mxCell>
    <mxCell id="edge21" style="html=1;endArrow=none;dashed=0;endFill=0;startArrow=none;startFill=0;fillColor=black;strokeColor=black;strokeWidth=1;rounded=0;exitX=0.0000;exitY=0.9644;entryX=0.6210;entryY=0.0000;" parent="1" edge="1" source="node27" target="node25">
      <mxGeometry as="geometry" relative="1">
        <mxPoint x="751.41" y="251.69000000000005" as="sourcePoint" />
        <mxPoint x="691.36" y="303.81000000000006" as="targetPoint" />
      </mxGeometry>
    </mxCell>
    <mxCell id="edge22" style="html=1;endArrow=none;dashed=0;endFill=0;startArrow=none;startFill=0;fillColor=black;strokeColor=black;strokeWidth=1;rounded=0;exitX=0.0000;exitY=0.6412;entryX=0.7715;entryY=0.0000;" parent="1" edge="1" source="node28" target="node29">
      <mxGeometry as="geometry" relative="1">
        <mxPoint x="841.39" y="420.62" as="sourcePoint" />
        <mxPoint x="524.63" y="493.99" as="targetPoint" />
      </mxGeometry>
    </mxCell>
    <mxCell id="edge45" style="html=1;endArrow=none;dashed=0;endFill=0;startArrow=none;startFill=0;fillColor=black;strokeColor=black;strokeWidth=1;rounded=0;exitX=0.5000;exitY=1.0000;entryX=0.5000;entryY=0.0000;" parent="1" edge="1" source="node29" target="node39">
      <mxGeometry as="geometry" relative="1">
        <mxPoint x="477.25" y="531.4" as="sourcePoint" />
        <mxPoint x="477.25" y="566.88" as="targetPoint" />
      </mxGeometry>
    </mxCell>
    <mxCell id="edge23" style="html=1;endArrow=none;dashed=0;endFill=0;startArrow=none;startFill=0;fillColor=black;strokeColor=black;strokeWidth=1;rounded=0;exitX=0.5000;exitY=1.0000;entryX=0.5000;entryY=0.0000;" parent="1" edge="1" source="node30" target="node19">
      <mxGeometry as="geometry" relative="1">
        <mxPoint x="1249.25" y="253.46000000000004" as="sourcePoint" />
        <mxPoint x="1249.25" y="297.38" as="targetPoint" />
      </mxGeometry>
    </mxCell>
    <mxCell id="edge24" style="html=1;endArrow=none;dashed=0;endFill=0;startArrow=none;startFill=0;fillColor=black;strokeColor=black;strokeWidth=1;rounded=0;exitX=1.0000;exitY=0.7577;entryX=0.3132;entryY=0.0000;" parent="1" edge="1" source="node31" target="node32">
      <mxGeometry as="geometry" relative="1">
        <mxPoint x="113.01" y="425.63" as="sourcePoint" />
        <mxPoint x="251.65" y="489.86" as="targetPoint" />
      </mxGeometry>
    </mxCell>
    <mxCell id="edge47" style="html=1;endArrow=none;dashed=0;endFill=0;startArrow=none;startFill=0;fillColor=black;strokeColor=black;strokeWidth=1;rounded=0;exitX=0.5000;exitY=1.0000;entryX=0.5000;entryY=0.0000;" parent="1" edge="1" source="node32" target="node42">
      <mxGeometry as="geometry" relative="1">
        <mxPoint x="284.25" y="531.4" as="sourcePoint" />
        <mxPoint x="284.25" y="575.61" as="targetPoint" />
      </mxGeometry>
    </mxCell>
    <mxCell id="edge25" style="html=1;endArrow=none;dashed=0;endFill=0;startArrow=none;startFill=0;fillColor=black;strokeColor=black;strokeWidth=1;rounded=0;exitX=0.5000;exitY=1.0000;entryX=0.5000;entryY=0.0000;" parent="1" edge="1" source="node33" target="node29">
      <mxGeometry as="geometry" relative="1">
        <mxPoint x="477.25" y="444.83000000000004" as="sourcePoint" />
        <mxPoint x="477.25" y="480.40999999999997" as="targetPoint" />
      </mxGeometry>
    </mxCell>
    <mxCell id="edge26" style="html=1;endArrow=none;dashed=0;endFill=0;startArrow=none;startFill=0;fillColor=black;strokeColor=black;strokeWidth=1;rounded=0;exitX=0.5000;exitY=1.0000;entryX=0.5000;entryY=0.0000;" parent="1" edge="1" source="node34" target="node35">
      <mxGeometry as="geometry" relative="1">
        <mxPoint x="1056.25" y="444.83000000000004" as="sourcePoint" />
        <mxPoint x="1056.25" y="480.40999999999997" as="targetPoint" />
      </mxGeometry>
    </mxCell>
    <mxCell id="edge48" style="html=1;endArrow=none;dashed=0;endFill=0;startArrow=none;startFill=0;fillColor=black;strokeColor=black;strokeWidth=1;rounded=0;exitX=0.5000;exitY=1.0000;entryX=0.5000;entryY=0.0000;" parent="1" edge="1" source="node35" target="node43">
      <mxGeometry as="geometry" relative="1">
        <mxPoint x="1056.25" y="531.4" as="sourcePoint" />
        <mxPoint x="1056.25" y="575.61" as="targetPoint" />
      </mxGeometry>
    </mxCell>
    <mxCell id="edge27" style="html=1;endArrow=none;dashed=0;endFill=0;startArrow=none;startFill=0;fillColor=black;strokeColor=black;strokeWidth=1;rounded=0;exitX=0.5000;exitY=1.0000;entryX=0.5000;entryY=0.0000;" parent="1" edge="1" source="node36" target="node32">
      <mxGeometry as="geometry" relative="1">
        <mxPoint x="284.25" y="444.83000000000004" as="sourcePoint" />
        <mxPoint x="284.25" y="480.40999999999997" as="targetPoint" />
      </mxGeometry>
    </mxCell>
    <mxCell id="edge28" style="html=1;endArrow=none;dashed=0;endFill=0;startArrow=none;startFill=0;fillColor=black;strokeColor=black;strokeWidth=1;rounded=0;exitX=0.5000;exitY=1.0000;entryX=0.5000;entryY=0.0000;" parent="1" edge="1" source="node37" target="node38">
      <mxGeometry as="geometry" relative="1">
        <mxPoint x="670.25" y="445.20000000000005" as="sourcePoint" />
        <mxPoint x="670.25" y="663.35" as="targetPoint" />
      </mxGeometry>
    </mxCell>
    <mxCell id="edge50" style="html=1;endArrow=none;dashed=0;endFill=0;startArrow=none;startFill=0;fillColor=black;strokeColor=black;strokeWidth=1;rounded=0;exitX=0.5000;exitY=1.0000;entryX=0.5000;entryY=0.0000;" parent="1" edge="1" source="node38" target="node46">
      <mxGeometry as="geometry" relative="1">
        <mxPoint x="670.25" y="714.23" as="sourcePoint" />
        <mxPoint x="670.25" y="758.44" as="targetPoint" />
      </mxGeometry>
    </mxCell>
    <mxCell id="edge29" style="html=1;endArrow=none;dashed=0;endFill=0;startArrow=none;startFill=0;fillColor=black;strokeColor=black;strokeWidth=1;rounded=0;exitX=0.5000;exitY=1.0000;entryX=0.5000;entryY=0.0000;" parent="1" edge="1" source="node39" target="node40">
      <mxGeometry as="geometry" relative="1">
        <mxPoint x="477.25" y="627.6600000000001" as="sourcePoint" />
        <mxPoint x="477.25" y="663.24" as="targetPoint" />
      </mxGeometry>
    </mxCell>
    <mxCell id="edge49" style="html=1;endArrow=none;dashed=0;endFill=0;startArrow=none;startFill=0;fillColor=black;strokeColor=black;strokeWidth=1;rounded=0;exitX=0.5000;exitY=1.0000;entryX=0.5000;entryY=0.0000;" parent="1" edge="1" source="node40" target="node44">
      <mxGeometry as="geometry" relative="1">
        <mxPoint x="477.25" y="714.23" as="sourcePoint" />
        <mxPoint x="477.25" y="749.71" as="targetPoint" />
      </mxGeometry>
    </mxCell>
    <mxCell id="edge30" style="html=1;endArrow=none;dashed=0;endFill=0;startArrow=none;startFill=0;fillColor=black;strokeColor=black;strokeWidth=1;rounded=0;exitX=0.0000;exitY=0.7577;entryX=0.6868;entryY=0.0000;" parent="1" edge="1" source="node41" target="node35">
      <mxGeometry as="geometry" relative="1">
        <mxPoint x="1227.49" y="425.63" as="sourcePoint" />
        <mxPoint x="1088.85" y="489.86" as="targetPoint" />
      </mxGeometry>
    </mxCell>
    <mxCell id="edge31" style="html=1;endArrow=none;dashed=0;endFill=0;startArrow=none;startFill=0;fillColor=black;strokeColor=black;strokeWidth=1;rounded=0;exitX=1.0000;exitY=0.7577;entryX=0.3132;entryY=0.0000;" parent="1" edge="1" source="node42" target="node40">
      <mxGeometry as="geometry" relative="1">
        <mxPoint x="306.01" y="608.46" as="sourcePoint" />
        <mxPoint x="444.65" y="672.69" as="targetPoint" />
      </mxGeometry>
    </mxCell>
    <mxCell id="edge32" style="html=1;endArrow=none;dashed=0;endFill=0;startArrow=none;startFill=0;fillColor=black;strokeColor=black;strokeWidth=1;rounded=0;exitX=0.0000;exitY=0.6409;entryX=0.7715;entryY=0.0000;" parent="1" edge="1" source="node43" target="node38">
      <mxGeometry as="geometry" relative="1">
        <mxPoint x="1034.39" y="603.44" as="sourcePoint" />
        <mxPoint x="717.63" y="676.8199999999999" as="targetPoint" />
      </mxGeometry>
    </mxCell>
    <mxCell id="edge33" style="html=1;endArrow=none;dashed=0;endFill=0;startArrow=none;startFill=0;fillColor=black;strokeColor=black;strokeWidth=1;rounded=0;exitX=1.0000;exitY=0.8530;entryX=0.3850;entryY=0.0000;" parent="1" edge="1" source="node44" target="node45">
      <mxGeometry as="geometry" relative="1">
        <mxPoint x="499.03" y="801.5" as="sourcePoint" />
        <mxPoint x="553.19" y="851.94" as="targetPoint" />
      </mxGeometry>
    </mxCell>
    <mxCell id="edge51" style="html=1;endArrow=none;dashed=0;endFill=0;startArrow=none;startFill=0;fillColor=black;strokeColor=black;strokeWidth=1;rounded=0;exitX=0.5000;exitY=1.0000;entryX=0.5000;entryY=0.0000;" parent="1" edge="1" source="node45" target="node47">
      <mxGeometry as="geometry" relative="1">
        <mxPoint x="573.25" y="897.29" as="sourcePoint" />
        <mxPoint x="573.25" y="932.39" as="targetPoint" />
      </mxGeometry>
    </mxCell>
    <mxCell id="edge34" style="html=1;endArrow=none;dashed=0;endFill=0;startArrow=none;startFill=0;fillColor=black;strokeColor=black;strokeWidth=1;rounded=0;exitX=0.0000;exitY=0.9847;entryX=0.6154;entryY=0.0000;" parent="1" edge="1" source="node46" target="node45">
      <mxGeometry as="geometry" relative="1">
        <mxPoint x="648.72" y="801.05" as="sourcePoint" />
        <mxPoint x="593.39" y="852.05" as="targetPoint" />
      </mxGeometry>
    </mxCell>
  </root>
</mxGraphModel>